odoo/addons/project_task_markdown/README.rst
odoo/addons/project_task_markdown/__init__.py
odoo/addons/project_task_markdown/__manifest__.py
odoo/addons/project_task_markdown/description/icon.png
odoo/addons/project_task_markdown/i18n/it.po
odoo/addons/project_task_markdown/i18n/project_task_markdown.pot
odoo/addons/project_task_markdown/models/__init__.py
odoo/addons/project_task_markdown/models/project_task.py
odoo/addons/project_task_markdown/readme/CONTRIBUTORS.rst
odoo/addons/project_task_markdown/readme/DESCRIPTION.rst
odoo/addons/project_task_markdown/readme/ROADMAP.rst
odoo/addons/project_task_markdown/readme/USAGE.rst
odoo/addons/project_task_markdown/static/description/icon.png
odoo/addons/project_task_markdown/static/description/index.html
odoo/addons/project_task_markdown/views/project_task.xml
odoo13_addon_project_task_markdown-13.0.1.0.1.dev10.dist-info/METADATA
odoo13_addon_project_task_markdown-13.0.1.0.1.dev10.dist-info/WHEEL
odoo13_addon_project_task_markdown-13.0.1.0.1.dev10.dist-info/top_level.txt
odoo13_addon_project_task_markdown-13.0.1.0.1.dev10.dist-info/RECORD
